MANIFEST.in
RELEASE-VERSION
setup.py
version.py
pythonsite_dotenv.egg-info/PKG-INFO
pythonsite_dotenv.egg-info/SOURCES.txt
pythonsite_dotenv.egg-info/dependency_links.txt
pythonsite_dotenv.egg-info/requires.txt
pythonsite_dotenv.egg-info/top_level.txt
sitecustomize/__init__.py