Metadata-Version: 1.0
Name: pythonsite-dotenv
Version: 0.1
Summary: Extend environment when invoking python
Home-page: https://github.com/urga/pythonsite-dotenv
Author: Dries Desmet
Author-email: dries@urga.be
License: UNKNOWN
Platform: UNKNOWN
